MyTube/__init__.py
MyTube/comments.py
MyTube/downloader.py
MyTube/errors.py
MyTube/playlist.py
MyTube/playlist_manager.py
MyTube/stream.py
MyTube/streams_manager.py
MyTube/subtitles.py
MyTube/utils.py
MyTube/youtube.py
mytube_dlp-2.1.0.dist-info/METADATA
mytube_dlp-2.1.0.dist-info/WHEEL
mytube_dlp-2.1.0.dist-info/top_level.txt
mytube_dlp-2.1.0.dist-info/RECORD
