Metadata-Version: 2.4
Name: MyTube_dlp
Version: 2.1.0
Summary: Python YouTube Downloader
Home-page: https://github.com/SuperZombi/MyTube
Author: Super_Zombi
Author-email: super.zombi.yt@gmail.com
Project-URL: Documentation, https://superzombi.github.io/MyTube/
Classifier: Programming Language :: Python :: 3
Classifier: License :: OSI Approved :: MIT License
Classifier: Operating System :: OS Independent
Requires-Python: >=3.9
Requires-Dist: yt-dlp
Requires-Dist: aiohttp
Requires-Dist: requests
Requires-Dist: Pillow
Dynamic: author
Dynamic: author-email
Dynamic: classifier
Dynamic: description
Dynamic: description-content-type
Dynamic: home-page
Dynamic: project-url
Dynamic: requires-dist
Dynamic: requires-python
Dynamic: summary
